Metadata-Version: 2.1
Name: texpack
Version: 1.0.0a1
Summary: Pack LaTeX Files into Single .tex File
Home-page: https://github.com/Mya-Mya/texpack
Author: Mya-Mya
License: MIT
Keywords: LaTeX,tex,academic
Classifier: License :: OSI Approved :: MIT License
Classifier: Programming Language :: Python :: 3
Classifier: Topic :: Text Processing :: Markup :: LaTeX
Classifier: Intended Audience :: Science/Research
Classifier: Topic :: Utilities
Classifier: Topic :: Education
License-File: LICENSE
